{"appleSKU":"","appleTeamID":"","enableCodelessAutoInitialization":true,"enableUnityGamingServicesAutoInitialization":true,"products":[{"id":"chainsawpremium","type":0,"storeIDs":[],"defaultDescription":{"googleLocale":4,"title":"chainsawpremium","description":"No ad No limit"},"screenshotPath":"","applePriceTier":0,"googlePrice":{"data":[0,0,0,0],"num":0.0},"pricingTemplateID":"","descriptions":[{"googleLocale":12,"title":"\\uccb4\\uc778\\uc18c\\ub9e8\\ud504\\ub9ac\\ubbf8\\uc5c4","description":"\\uad11\\uace0\\uc81c\\uac70, \\ucf00\\ub9ad\\ub2f9 \\uc990\\uaca8\\ucc3e\\uae30 \\ubb34\\uc81c\\ud55c"}],"udpPrice":{"data":[0,0,0,0],"num":0.0},"payouts":[]}]}